convbase/__init__.py
convbase/cli.py
convbase/lib.py
convbase-0.2.0.dist-info/WHEEL
convbase-0.2.0.dist-info/entry_points.txt
convbase-0.2.0.dist-info/METADATA
convbase-0.2.0.dist-info/RECORD
