Metadata-Version: 2.3
Name: convbase
Version: 0.2.0
Summary: Base conversion command line utility.
Keywords: 
Author: Kyle O'Malley
Author-email: Kyle O'Malley <j.kyle.omalley@gmail.com>
Classifier: Development Status :: 4 - Beta
Classifier: Environment :: Console
Classifier: Operating System :: OS Independent
Classifier: License :: OSI Approved :: MIT License
Classifier: Programming Language :: Python
Classifier: Programming Language :: Python :: 3.10
Classifier: Programming Language :: Python :: 3.11
Classifier: Programming Language :: Python :: 3.12
Classifier: Programming Language :: Python :: 3.13
Classifier: Programming Language :: Python :: 3.14
Classifier: Programming Language :: Python :: 3 :: Only
Classifier: Topic :: Utilities
Requires-Dist: click
Requires-Python: >=3.10
Project-URL: Documentation, https://github.com/jkomalley/convbase#readme
Project-URL: Issues, https://github.com/jkomalley/convbase/issues
Project-URL: Source, https://github.com/jkomalley/convbase
